{"assets/icons/ic_default_image.png":["assets/icons/ic_default_image.png"],"assets/icons/icon_delete.svg":["assets/icons/icon_delete.svg"],"assets/icons/icon_disconect.svg":["assets/icons/icon_disconect.svg"],"assets/icons/icon_empty.svg":["assets/icons/icon_empty.svg"],"assets/icons/icon_fly.svg":["assets/icons/icon_fly.svg"],"assets/icons/icon_heart.png":["assets/icons/icon_heart.png"],"assets/icons/icon_heart_border.png":["assets/icons/icon_heart_border.png"],"assets/icons/icon_heart_half.png":["assets/icons/icon_heart_half.png"],"assets/icons/icon_home.svg":["assets/icons/icon_home.svg"],"assets/icons/icon_language.svg":["assets/icons/icon_language.svg"],"assets/icons/icon_logout.svg":["assets/icons/icon_logout.svg"],"assets/icons/icon_memory.svg":["assets/icons/icon_memory.svg"],"assets/icons/icon_moon.svg":["assets/icons/icon_moon.svg"],"assets/icons/icon_notification.svg":["assets/icons/icon_notification.svg"],"assets/icons/icon_reminder.svg":["assets/icons/icon_reminder.svg"],"assets/icons/icon_user.svg":["assets/icons/icon_user.svg"],"assets/icons/icon_vote.svg":["assets/icons/icon_vote.svg"],"assets/icons/notification.svg":["assets/icons/notification.svg"],"assets/icons/premium.png":["assets/icons/premium.png"],"assets/icons/setting.svg":["assets/icons/setting.svg"],"assets/icons/share.svg":["assets/icons/share.svg"],"assets/lotties/couple.json":["assets/lotties/couple.json"],"packages/cupertino_icons/assets/CupertinoIcons.ttf":["packages/cupertino_icons/assets/CupertinoIcons.ttf"],"packages/eva_icons_flutter/lib/fonts/Eva-Icons.ttf":["packages/eva_icons_flutter/lib/fonts/Eva-Icons.ttf"],"packages/fluttertoast/assets/toastify.css":["packages/fluttertoast/assets/toastify.css"],"packages/fluttertoast/assets/toastify.js":["packages/fluttertoast/assets/toastify.js"]}